{"parent":"minecraft:item/generated","textures":{"layer0":"minecraft:item/leather_horse_armor"},"overrides":[{"predicate":{"custom_model_data":1},"model":"modelengine:ballista/head"},{"predicate":{"custom_model_data":2},"model":"modelengine:ballista/body"},{"predicate":{"custom_model_data":3},"model":"modelengine:cannon/body"},{"predicate":{"custom_model_data":4},"model":"modelengine:cannon/tube"},{"predicate":{"custom_model_data":5},"model":"modelengine:cannon/left"},{"predicate":{"custom_model_data":6},"model":"modelengine:cannon/right"},{"predicate":{"custom_model_data":7},"model":"modelengine:catapultrig/body"},{"predicate":{"custom_model_data":8},"model":"modelengine:catapultrig/realer"},{"predicate":{"custom_model_data":9},"model":"modelengine:catapultrig/backweel"},{"predicate":{"custom_model_data":10},"model":"modelengine:catapultrig/catapultarm"},{"predicate":{"custom_model_data":11},"model":"modelengine:catapultrig/frontweel"},{"predicate":{"custom_model_data":12},"model":"modelengine:catapultrig/rope"},{"predicate":{"custom_model_data":13},"model":"modelengine:catapultrig/tower"},{"predicate":{"custom_model_data":14},"model":"modelengine:catapultrig/horsething"},{"predicate":{"custom_model_data":15},"model":"modelengine:twentycents_trebuchet/bottom"},{"predicate":{"custom_model_data":16},"model":"modelengine:twentycents_trebuchet/loadingboard"},{"predicate":{"custom_model_data":17},"model":"modelengine:twentycents_trebuchet/lefttower"},{"predicate":{"custom_model_data":18},"model":"modelengine:twentycents_trebuchet/righttower"},{"predicate":{"custom_model_data":19},"model":"modelengine:twentycents_trebuchet/arm"},{"predicate":{"custom_model_data":20},"model":"modelengine:twentycents_trebuchet/weight"}]}